dogesay-1.0.0.dist-info/WHEEL
dogesay-1.0.0.dist-info/entry_points.txt
dogesay-1.0.0.dist-info/DESCRIPTION.rst
dogesay-1.0.0.dist-info/top_level.txt
dogesay-1.0.0.dist-info/METADATA
dogesay-1.0.0.dist-info/RECORD
dogesay-1.0.0.dist-info/metadata.json
dogesay/__init__.py
dogesay/script.py
dogesay/static/doge.txt
