Metadata-Version: 2.0
Name: dogesay
Version: 1.0.0
Summary: Like cowsay but doge
Home-page: https://github.com/jinnovation/dogesay
Author: Jonathan Jin
Author-email: jonathan@jjin.me
License: MIT
Download-URL: https://github.com/jinnovation/dogesay/tarball/1.0
Platform: UNKNOWN
Classifier: Development Status :: 4 - Beta
Classifier: Intended Audience :: End Users/Desktop
Classifier: Intended Audience :: Developers
Classifier: Topic :: Games/Entertainment
Classifier: License :: OSI Approved :: MIT License
Classifier: Programming Language :: Python :: 2
Classifier: Programming Language :: Python :: 3
